setup.cfg
setup.py
flexable/__init__.py
flexable/forms.py
flexable/plugin.py
flexable/template.py
flexable.egg-info/PKG-INFO
flexable.egg-info/SOURCES.txt
flexable.egg-info/dependency_links.txt
flexable.egg-info/entry_points.txt
flexable.egg-info/not-zip-safe
flexable.egg-info/requires.txt
flexable.egg-info/top_level.txt
test/test_forms.py
test/test_template.py
